Metadata-Version: 2.1
Name: pollination-annual-daylight-en17037.viz
Version: 0.1.15
Summary: Annual daylight EN17037 recipe for Pollination.
Home-page: https://github.com/pollination/annual-daylight-en17037
Author: ladybug-tools
Author-email: info@ladybug.tools
Maintainer: mostapha, ladybug-tools
Maintainer-email: mostapha@ladybug.tools, info@ladybug.tools
License: PolyForm Shield License 1.0.0, https://polyformproject.org/wp-content/uploads/2020/06/PolyForm-Shield-1.0.0.txt
Project-URL: icon, https://raw.githubusercontent.com/ladybug-tools/artwork/master/icons_components/honeybee/png/annualrecipe.png
Project-URL: docker, https://hub.docker.com/r/ladybugtools/honeybee-radiance
Keywords: honeybee,radiance,ladybug-tools,daylight,annual-daylight-en17037
License-File: LICENSE
Requires-Dist: pollination-two-phase-daylight-coefficient (>=1.1.23)
Requires-Dist: pollination-ladybug (>=0.2.2)
Provides-Extra: viz
Requires-Dist: pollination-honeybee-display (>=0.1.12) ; extra == 'viz'
